arduino_colab_kernel/magic_board.py
arduino_colab_kernel/magic_code.py
arduino_colab_kernel/magic_project.py
arduino_colab_kernel/magic_serial.py
arduino_colab_kernel/backends/__init__.py
arduino_colab_kernel/backends/local_backend.py
arduino_colab_kernel/backends/protocol.py
arduino_colab_kernel/backends/remote_backend.py
arduino_colab_kernel/board/__init__.py
arduino_colab_kernel/board/board.py
arduino_colab_kernel/board/board_manager.py
arduino_colab_kernel/bridge/__init__.py
arduino_colab_kernel/bridge/bridge.py
arduino_colab_kernel/bridge/serial_port.py
arduino_colab_kernel/code/__init__.py
arduino_colab_kernel/code/code_manager.py
arduino_colab_kernel/code/ino_generator.py
arduino_colab_kernel/demos/demo.ipynb
arduino_colab_kernel/demos/projects/demo/demo.ino
arduino_colab_kernel/demos/projects/demo/demo.json
arduino_colab_kernel/demos/projects/demo/logs/upload.log
arduino_colab_kernel/demos/projects/sketch/sketch.ino
arduino_colab_kernel/demos/projects/sketch/sketch.json
arduino_colab_kernel/demos/projects/sketch/logs/upload.log
arduino_colab_kernel/project/__init__.py
arduino_colab_kernel/project/config.py
arduino_colab_kernel/project/project_manager.py
arduino_colab_kernel/tools/LICENSE.txt
arduino_colab_kernel/tools/__init__.py
arduino_colab_kernel/tools/arduino-cli.exe
arduino_colab_kernel/tools/__pycache__/__init__.cpython-310.pyc
arduino_colab_kernel/tools/__pycache__/__init__.cpython-311.pyc
arduino_colab_kernel/utils/__init__.py
arduino_colab_kernel/utils/utils_cli.py
arduino_colab_kernel-0.1.53.dist-info/licenses/LICENSE
arduino_colab_kernel-0.1.53.dist-info/METADATA
arduino_colab_kernel-0.1.53.dist-info/WHEEL
arduino_colab_kernel-0.1.53.dist-info/top_level.txt
arduino_colab_kernel-0.1.53.dist-info/RECORD
