Metadata-Version: 2.4
Name: arduino-colab-kernel
Version: 0.1.53
Summary: Jupyter magics for Arduino/ESP32
Author-email: Jiri Konecny <jiri.konecny@vsb.cz>
License-Expression: MIT
Project-URL: Homepage, https://github.com/sgtkingo/ArduinoColab
Project-URL: Repository, https://github.com/sgtkingo/ArduinoColab
Project-URL: Issues, https://github.com/sgtkingo/ArduinoColab/issues
Keywords: arduino,esp32,jupyter,magics,notebook
Classifier: Development Status :: 3 - Alpha
Classifier: Intended Audience :: Developers
Classifier: Topic :: Software Development :: Embedded Systems
Classifier: Topic :: Education
Classifier: Programming Language :: Python :: 3
Classifier: Programming Language :: Python :: 3.10
Requires-Python: >=3.10
License-File: LICENSE
Requires-Dist: pyserial>=3.5
Requires-Dist: ipykernel
Requires-Dist: ipython
Dynamic: license-file
